./.gitignore
./PKG-INFO
./README.md
./env_example.txt
./language.json
./mcp_config.json
./package_name
./push_info.json
./pyproject.toml
./requirements.txt
./server.py
iflow_mcp_gkydev_twitter_mcp_server-0.1.0.dist-info/METADATA
iflow_mcp_gkydev_twitter_mcp_server-0.1.0.dist-info/WHEEL
iflow_mcp_gkydev_twitter_mcp_server-0.1.0.dist-info/entry_points.txt
iflow_mcp_gkydev_twitter_mcp_server-0.1.0.dist-info/RECORD
