Metadata-Version: 2.4
Name: iflow-mcp_gkydev_twitter-mcp-server
Version: 0.1.0
Summary: Twitter MCP Server using twikit - provides Twitter functionality through Model Context Protocol
Requires-Python: >=3.8
Requires-Dist: mcp>=1.0.0
Requires-Dist: pydantic>=2.0.0
Requires-Dist: python-dotenv>=1.0.0
Requires-Dist: twikit>=1.7.0
